sentinel/__init__.py
sentinel/chat_completions.py
sentinel/client.py
sentinel/exceptions.py
tests/__init__.py
tests/test_chat_completions.py
tests/test_client.py
yugenkairo_sentinel_sdk-1.0.0.dist-info/METADATA
yugenkairo_sentinel_sdk-1.0.0.dist-info/WHEEL
yugenkairo_sentinel_sdk-1.0.0.dist-info/top_level.txt
yugenkairo_sentinel_sdk-1.0.0.dist-info/RECORD
