Metadata-Version: 2.4
Name: yugenkairo-sentinel-sdk
Version: 1.0.0
Summary: Python SDK for Sentinel - Enterprise LLM Security Gateway with AI-powered threat detection and cryptographic data protection
Home-page: https://github.com/swayam8624/Sentinel
Author: Sentinel Team
Author-email: sentinel-team@yugenkairo.com
Project-URL: Documentation, https://swayam8624.github.io/Sentinel/
Project-URL: Source, https://github.com/swayam8624/Sentinel
Project-URL: Tracker, https://github.com/swayam8624/Sentinel/issues
Keywords: sentinel,llm,security,firewall,cryptography,pii,data-protection,ai-security,prompt-injection,rate-limiting,enterprise,compliance
Classifier: Development Status :: 5 - Production/Stable
Classifier: Intended Audience :: Developers
Classifier: Intended Audience :: Information Technology
Classifier: License :: OSI Approved :: Apache Software License
Classifier: Operating System :: OS Independent
Classifier: Programming Language :: Python :: 3
Classifier: Programming Language :: Python :: 3.8
Classifier: Programming Language :: Python :: 3.9
Classifier: Programming Language :: Python :: 3.10
Classifier: Programming Language :: Python :: 3.11
Classifier: Programming Language :: Python :: 3.12
Classifier: Topic :: Security
Classifier: Topic :: Security :: Cryptography
Classifier: Topic :: Software Development :: Libraries :: Python Modules
Classifier: Topic :: Internet :: WWW/HTTP :: HTTP Servers
Requires-Python: >=3.8
Requires-Dist: requests>=2.31.0
Requires-Dist: pydantic>=2.0.0
Requires-Dist: cryptography>=41.0.0
Provides-Extra: dev
Requires-Dist: pytest>=7.4.0; extra == "dev"
Requires-Dist: black>=23.0.0; extra == "dev"
Requires-Dist: flake8>=6.0.0; extra == "dev"
Requires-Dist: mypy>=1.5.0; extra == "dev"
Provides-Extra: enterprise
Requires-Dist: redis>=4.6.0; extra == "enterprise"
Requires-Dist: prometheus-client>=0.17.0; extra == "enterprise"
Dynamic: author
Dynamic: author-email
Dynamic: classifier
Dynamic: description
Dynamic: description-content-type
Dynamic: home-page
Dynamic: keywords
Dynamic: project-url
Dynamic: provides-extra
Dynamic: requires-dist
Dynamic: requires-python
Dynamic: summary
